dcode/__init__.py
dcode/cli.py
dcode/serializers.py
dcode/utils.py
dcodelib-0.0.1.dist-info/METADATA
dcodelib-0.0.1.dist-info/WHEEL
dcodelib-0.0.1.dist-info/entry_points.txt
dcodelib-0.0.1.dist-info/top_level.txt
dcodelib-0.0.1.dist-info/RECORD
