Metadata-Version: 2.1
Name: dcodelib
Version: 0.0.1
Summary: Collection of various serialization methods with cli
Home-page: https://github.com/trisongz/dcodelib
Author: Tri Songz
Author-email: ts@growthengineai.com
License: MIT Style
Platform: UNKNOWN
Classifier: Intended Audience :: Developers
Classifier: License :: OSI Approved :: MIT License
Classifier: Programming Language :: Python :: 3.6
Classifier: Topic :: Software Development :: Libraries
Requires-Python: >=3.6
Requires-Dist: pylogz
Requires-Dist: pyyaml
Requires-Dist: typer
Requires-Dist: boltons
